shw/__init__.py
shw/main.py
shw-1.0.dist-info/DESCRIPTION.rst
shw-1.0.dist-info/METADATA
shw-1.0.dist-info/RECORD
shw-1.0.dist-info/WHEEL
shw-1.0.dist-info/entry_points.txt
shw-1.0.dist-info/metadata.json
shw-1.0.dist-info/top_level.txt
