Metadata-Version: 2.0
Name: shw
Version: 1.0
Summary: a library for ssh & scp shortcut on linux
Home-page: https://github.com/WongChen/shw
Author: wong
Author-email: yachenwang4@gmail.com
License: MIT License
Keywords: ssh shortcut ubuntu
Platform: Linux
Platform: macOS
